touchv2/__init__.py
touchv2-1.1.dist-info/METADATA
touchv2-1.1.dist-info/WHEEL
touchv2-1.1.dist-info/top_level.txt
touchv2-1.1.dist-info/RECORD
